simplelogin.py
simplelogin_client-0.1.0.dist-info/licenses/LICENSE
simplelogin_client-0.1.0.dist-info/METADATA
simplelogin_client-0.1.0.dist-info/WHEEL
simplelogin_client-0.1.0.dist-info/top_level.txt
simplelogin_client-0.1.0.dist-info/RECORD
