Metadata-Version: 2.4
Name: simplelogin-client
Version: 0.1.0
Summary: A Python client for interacting with the SimpleLogin API.
Home-page: https://github.com/ChromeGenesis/simplelogin
Author: Genesis Chrome
Author-email: gnschrm@gmail.com
Classifier: Programming Language :: Python :: 3
Classifier: License :: OSI Approved :: GNU General Public License v3 (GPLv3)
Classifier: Operating System :: OS Independent
License-File: LICENSE
Requires-Dist: requests
Dynamic: author
Dynamic: author-email
Dynamic: classifier
Dynamic: description
Dynamic: description-content-type
Dynamic: home-page
Dynamic: license-file
Dynamic: requires-dist
Dynamic: summary
